cuallee/__init__.py
cuallee/bigquery_validation.py
cuallee/duckdb_validation.py
cuallee/pandas_validation.py
cuallee/polars_validation.py
cuallee/pyspark_validation.py
cuallee/snowpark_validation.py
cuallee/utils.py
cuallee/iso/__init__.py
cuallee/iso/checks.py
cuallee_aws-0.5.1.dist-info/LICENSE
cuallee_aws-0.5.1.dist-info/METADATA
cuallee_aws-0.5.1.dist-info/WHEEL
cuallee_aws-0.5.1.dist-info/top_level.txt
cuallee_aws-0.5.1.dist-info/RECORD
