Metadata-Version: 2.1
Name: cuallee-aws
Version: 0.5.1
Summary: Python library for data validation on DataFrame APIs including Snowflake/Snowpark, Apache/PySpark and Pandas/DataFrame.
Author-email: Virginie Grosboillot <vestalisvirginis@gmail.com>, Herminio Vazquez <canimus@gmail.com>, Demetrius Albuquerque <dcalbuquerque86@gmail.com>
Project-URL: Homepage, https://github.com/maltzsama/cuallee
Project-URL: Bug Tracker, https://github.com/maltzsama/cuallee
Classifier: Programming Language :: Python :: 3
Classifier: License :: OSI Approved :: MIT License
Classifier: Operating System :: OS Independent
Requires-Python: >=3.8
License-File: LICENSE
Requires-Dist: colorama >=0.4.6
Requires-Dist: toolz >=0.12.0
Requires-Dist: pygments >=2.15.1
Requires-Dist: requests >=2.28.2
Requires-Dist: pandas >=1.5.3
Provides-Extra: bigquery
Requires-Dist: google-cloud-bigquery >=3.10.0 ; extra == 'bigquery'
Requires-Dist: pyarrow >=11.0.0 ; extra == 'bigquery'
Provides-Extra: duckdb
Requires-Dist: duckdb >=0.7.1 ; extra == 'duckdb'
Provides-Extra: pandas
Requires-Dist: pandas >=2.0.1 ; extra == 'pandas'
Provides-Extra: polars
Requires-Dist: polars >=0.15.7 ; extra == 'polars'
Provides-Extra: pyspark
Requires-Dist: pyspark >=3.4.0 ; extra == 'pyspark'
Provides-Extra: snowpark
Requires-Dist: snowflake-snowpark-python >=1.4.0 ; extra == 'snowpark'
Requires-Dist: pyarrow >=10.0.1 ; extra == 'snowpark'
Provides-Extra: test
Requires-Dist: pytest ; extra == 'test'
Requires-Dist: pytest-cov ; extra == 'test'
Requires-Dist: pendulum >=2.1.2 ; extra == 'test'
